repomirror/__init__.py
repomirror/config.py
repomirror/constants.py
repomirror/logger.py
repomirror/sync.py
repomirror/fetcher/__init__.py
repomirror/fetcher/_base.py
repomirror/fetcher/ftp.py
repomirror/fetcher/rsync.py
repomirror/fetcher/rsync_returns.py
repomirror/utils/__init__.py
repomirror-1.0.4.data/scripts/reposync
repomirror-1.0.4.dist-info/LICENSE
repomirror-1.0.4.dist-info/METADATA
repomirror-1.0.4.dist-info/WHEEL
repomirror-1.0.4.dist-info/top_level.txt
repomirror-1.0.4.dist-info/RECORD
