Metadata-Version: 2.1
Name: repomirror
Version: 1.0.4
Summary: Clone/mirror multiple Linux distro/BSD flavor/etc. repositories to a local server
Home-page: https://git.square-r00t.net/RepoMirror/
Author: Brent S.
Author-email: bts@square-r00t.net
License: UNKNOWN
Project-URL: Documentation, https://git.square-r00t.net/RepoMirror/tree/README
Project-URL: Source, https://git.square-r00t.net/RepoMirror/
Project-URL: Tracker, https://bugs.square-r00t.net/index.php?project=14
Platform: UNKNOWN
Classifier: Environment :: Console
Classifier: Intended Audience :: Developers
Classifier: Intended Audience :: Information Technology
Classifier: Intended Audience :: System Administrators
Classifier: License :: OSI Approved :: GNU General Public License v3 or later (GPLv3+)
Classifier: Operating System :: POSIX :: BSD
Classifier: Operating System :: POSIX :: Linux
Classifier: Programming Language :: Python :: 3
Classifier: Programming Language :: Python :: 3.7
Classifier: Programming Language :: Python :: 3.8
Classifier: Programming Language :: Python :: 3.9
Classifier: Programming Language :: Python :: 3 :: Only
Classifier: Topic :: Internet
Classifier: Topic :: Software Development :: Build Tools
Classifier: Topic :: System :: Archiving :: Mirroring
Classifier: Topic :: System :: Installation/Setup
Classifier: Topic :: System :: Software Distribution
Classifier: Topic :: System :: Systems Administration
Requires-Python: >=3.7
Requires-Dist: lxml
Requires-Dist: psutil
Requires-Dist: requests
Requires-Dist: beautifulsoup4
